jours_feries_france/__init__.py
jours_feries_france/compute.py
jours_feries_france-0.5.dist-info/LICENSE
jours_feries_france-0.5.dist-info/METADATA
jours_feries_france-0.5.dist-info/WHEEL
jours_feries_france-0.5.dist-info/top_level.txt
jours_feries_france-0.5.dist-info/RECORD
