Metadata-Version: 2.1
Name: jours-feries-france
Version: 0.5
Summary: Get bank holidays for France
Home-page: https://github.com/AntoineAugusti/jours-feries-france
Author: Antoine Augusti
Author-email: hi@antoine-augusti.fr
License: MIT
Keywords: bank-holidays,jours-feries,france
Platform: UNKNOWN
Classifier: Development Status :: 3 - Alpha
Classifier: Intended Audience :: Developers
Classifier: License :: OSI Approved :: MIT License
Classifier: Programming Language :: Python :: 3
Classifier: Programming Language :: Python :: 2.7
Classifier: Programming Language :: Python :: 3.5
Classifier: Programming Language :: Python :: 3.6
Classifier: Programming Language :: Python :: 3.7
Requires-Python: >=2.7,<4
Provides-Extra: dev
Requires-Dist: nose ; extra == 'dev'
